probdiffeq/__init__.py
probdiffeq/_version.py
probdiffeq/ivpsolve.py
probdiffeq/ivpsolvers.py
probdiffeq/stats.py
probdiffeq/taylor.py
probdiffeq/backend/__init__.py
probdiffeq/backend/abc.py
probdiffeq/backend/config.py
probdiffeq/backend/containers.py
probdiffeq/backend/control_flow.py
probdiffeq/backend/functools.py
probdiffeq/backend/itertools.py
probdiffeq/backend/linalg.py
probdiffeq/backend/numpy.py
probdiffeq/backend/ode.py
probdiffeq/backend/random.py
probdiffeq/backend/special.py
probdiffeq/backend/stats.py
probdiffeq/backend/testing.py
probdiffeq/backend/tree_array_util.py
probdiffeq/backend/tree_util.py
probdiffeq/backend/typing.py
probdiffeq/backend/warnings.py
probdiffeq/impl/__init__.py
probdiffeq/impl/_conditional.py
probdiffeq/impl/_linearise.py
probdiffeq/impl/_normal.py
probdiffeq/impl/_prototypes.py
probdiffeq/impl/_stats.py
probdiffeq/impl/impl.py
probdiffeq/util/__init__.py
probdiffeq/util/cholesky_util.py
probdiffeq/util/filter_util.py
probdiffeq/util/doc_util/__init__.py
probdiffeq/util/doc_util/info.py
probdiffeq-0.8.2.dist-info/licenses/LICENSE
probdiffeq-0.8.2.dist-info/METADATA
probdiffeq-0.8.2.dist-info/WHEEL
probdiffeq-0.8.2.dist-info/top_level.txt
probdiffeq-0.8.2.dist-info/RECORD
