Metadata-Version: 2.4
Name: probdiffeq
Version: 0.8.2
Summary: Probabilistic numerical solvers for differential equations
Author-email: Nicholas Krämer <pekra@dtu.dk>
Project-URL: Documentation, https://pnkraemer.github.io/probdiffeq/
Project-URL: Issue tracker, https://github.com/pnkraemer/probdiffeq/issues
Classifier: License :: OSI Approved :: MIT License
Classifier: Operating System :: OS Independent
Classifier: Programming Language :: Python
Classifier: Programming Language :: Python :: 3.11
Classifier: Programming Language :: Python :: 3.12
Classifier: Programming Language :: Python :: 3.13
Requires-Python: >=3.11
License-File: LICENSE
Requires-Dist: mypy_extensions
Requires-Dist: typing_extensions
Provides-Extra: cpu
Requires-Dist: jax[cpu]; extra == "cpu"
Provides-Extra: test
Requires-Dist: pytest; extra == "test"
Requires-Dist: pytest-xdist; extra == "test"
Requires-Dist: pytest-cases; extra == "test"
Requires-Dist: diffeqzoo; extra == "test"
Requires-Dist: diffrax; extra == "test"
Requires-Dist: equinox; extra == "test"
Provides-Extra: format-and-lint
Requires-Dist: pre-commit; extra == "format-and-lint"
Provides-Extra: doc
Requires-Dist: jupytext; extra == "doc"
Requires-Dist: jupyter; extra == "doc"
Requires-Dist: matplotlib; extra == "doc"
Requires-Dist: jupytext; extra == "doc"
Requires-Dist: diffeqzoo; extra == "doc"
Requires-Dist: tueplots; extra == "doc"
Requires-Dist: tqdm; extra == "doc"
Requires-Dist: optax; extra == "doc"
Requires-Dist: blackjax>=1.0.0; extra == "doc"
Requires-Dist: diffrax; extra == "doc"
Requires-Dist: numba; extra == "doc"
Requires-Dist: mkdocs; extra == "doc"
Requires-Dist: mkdocs-material; extra == "doc"
Requires-Dist: mkdocs-exclude; extra == "doc"
Requires-Dist: mkdocstrings-python; extra == "doc"
Requires-Dist: mkdocstrings; extra == "doc"
Requires-Dist: mkdocs-jupyter; extra == "doc"
Dynamic: license-file
